{"ID":457,"Name":"user-457","Timezone":"Asia/Shanghai","CreatedAt":"2025-06-22T22:36:29.947829+04:00"},
{"ID":807,"Name":"user-807","Timezone":"Asia/Shanghai","CreatedAt":"2025-06-22T22:36:30.047665+04:00"},
{"ID":448,"Name":"user-448","Timezone":"Asia/Shanghai","CreatedAt":"2025-06-22T22:36:30.147806+04:00"},
{"ID":370,"Name":"user-370","Timezone":"Asia/Shanghai","CreatedAt":"2025-06-22T22:36:30.247647+04:00"},
{"ID":976,"Name":"user-976","Timezone":"Asia/Shanghai","CreatedAt":"2025-06-22T22:36:30.347783+04:00"},
{"ID":942,"Name":"user-942","Timezone":"Asia/Shanghai","CreatedAt":"2025-06-22T22:36:30.447617+04:00"},
{"ID":909,"Name":"user-909","Timezone":"Asia/Shanghai","CreatedAt":"2025-06-22T22:36:30.547763+04:00"},
{"ID":3,"Name":"user-3","Timezone":"Asia/Shanghai","CreatedAt":"2025-06-22T22:36:30.647707+04:00"},
{"ID":302,"Name":"user-302","Timezone":"Asia/Shanghai","CreatedAt":"2025-06-22T22:36:30.747823+04:00"},
{"ID":654,"Name":"user-654","Timezone":"Asia/Shanghai","CreatedAt":"2025-06-22T22:36:30.847615+04:00"},
{"ID":329,"Name":"user-329","Timezone":"Asia/Shanghai","CreatedAt":"2025-06-22T22:36:30.947741+04:00"},
{"ID":420,"Name":"user-420","Timezone":"Asia/Shanghai","CreatedAt":"2025-06-22T22:36:31.047616+04:00"},
{"ID":789,"Name":"user-789","Timezone":"Asia/Shanghai","CreatedAt":"2025-06-22T22:36:31.147753+04:00"},
{"ID":138,"Name":"user-138","Timezone":"Asia/Shanghai","CreatedAt":"2025-06-22T22:36:31.247583+04:00"},
{"ID":987,"Name":"user-987","Timezone":"Asia/Shanghai","CreatedAt":"2025-06-22T22:36:31.34769+04:00"},
{"ID":506,"Name":"user-506","Timezone":"Asia/Shanghai","CreatedAt":"2025-06-22T22:36:31.447889+04:00"},
{"ID":665,"Name":"user-665","Timezone":"Asia/Shanghai","CreatedAt":"2025-06-22T22:36:31.54773+04:00"},
{"ID":104,"Name":"user-104","Timezone":"Asia/Shanghai","CreatedAt":"2025-06-22T22:36:31.647589+04:00"},
{"ID":634,"Name":"user-634","Timezone":"Asia/Shanghai","CreatedAt":"2025-06-22T22:36:31.747662+04:00"},
{"ID":501,"Name":"user-501","Timezone":"Asia/Shanghai","CreatedAt":"2025-06-22T22:36:31.847592+04:00"},
{"ID":471,"Name":"user-471","Timezone":"Asia/Shanghai","CreatedAt":"2025-06-22T22:36:31.947713+04:00"},
{"ID":653,"Name":"user-653","Timezone":"Asia/Shanghai","CreatedAt":"2025-06-22T22:36:32.047639+04:00"},
{"ID":573,"Name":"user-573","Timezone":"Asia/Shanghai","CreatedAt":"2025-06-22T22:36:32.147522+04:00"},
{"ID":563,"Name":"user-563","Timezone":"Asia/Shanghai","CreatedAt":"2025-06-22T22:36:32.247503+04:00"},
{"ID":49,"Name":"user-49","Timezone":"Asia/Shanghai","CreatedAt":"2025-06-22T22:36:32.347652+04:00"},
{"ID":196,"Name":"user-196","Timezone":"Asia/Shanghai","CreatedAt":"2025-06-22T22:36:32.447552+04:00"},
{"ID":929,"Name":"user-929","Timezone":"Asia/Shanghai","CreatedAt":"2025-06-22T22:36:32.547651+04:00"},
{"ID":139,"Name":"user-139","Timezone":"Asia/Shanghai","CreatedAt":"2025-06-22T22:36:32.647553+04:00"},
{"ID":685,"Name":"user-685","Timezone":"Asia/Shanghai","CreatedAt":"2025-06-22T22:36:32.747746+04:00"},
{"ID":564,"Name":"user-564","Timezone":"Asia/Shanghai","CreatedAt":"2025-06-22T22:36:32.847526+04:00"},
{"ID":606,"Name":"user-606","Timezone":"Asia/Shanghai","CreatedAt":"2025-06-22T22:36:32.947661+04:00"},
{"ID":660,"Name":"user-660","Timezone":"Asia/Shanghai","CreatedAt":"2025-06-22T22:36:33.047553+04:00"},
{"ID":914,"Name":"user-914","Timezone":"Asia/Shanghai","CreatedAt":"2025-06-22T22:36:33.147655+04:00"},
{"ID":937,"Name":"user-937","Timezone":"Asia/Shanghai","CreatedAt":"2025-06-22T22:36:33.247528+04:00"},
{"ID":334,"Name":"user-334","Timezone":"Asia/Shanghai","CreatedAt":"2025-06-22T22:36:33.347221+04:00"},
{"ID":946,"Name":"user-946","Timezone":"Asia/Shanghai","CreatedAt":"2025-06-22T22:36:33.447507+04:00"},
{"ID":173,"Name":"user-173","Timezone":"Asia/Shanghai","CreatedAt":"2025-06-22T22:36:33.547634+04:00"},
{"ID":412,"Name":"user-412","Timezone":"Asia/Shanghai","CreatedAt":"2025-06-22T22:36:33.64749+04:00"},
{"ID":235,"Name":"user-235","Timezone":"Asia/Shanghai","CreatedAt":"2025-06-22T22:36:33.747666+04:00"},
{"ID":833,"Name":"user-833","Timezone":"Asia/Shanghai","CreatedAt":"2025-06-22T22:36:33.847489+04:00"},
{"ID":90,"Name":"user-90","Timezone":"Asia/Shanghai","CreatedAt":"2025-06-22T22:36:33.947575+04:00"},
{"ID":246,"Name":"user-246","Timezone":"Asia/Shanghai","CreatedAt":"2025-06-22T22:36:59.073547+04:00"},
{"ID":32,"Name":"user-32","Timezone":"Asia/Shanghai","CreatedAt":"2025-06-22T22:36:59.17348+04:00"},
{"ID":954,"Name":"user-954","Timezone":"Asia/Shanghai","CreatedAt":"2025-06-22T22:36:59.273528+04:00"},
{"ID":498,"Name":"user-498","Timezone":"Asia/Shanghai","CreatedAt":"2025-06-22T22:36:59.373444+04:00"},
{"ID":475,"Name":"user-475","Timezone":"Asia/Shanghai","CreatedAt":"2025-06-22T22:36:59.473487+04:00"},
{"ID":238,"Name":"user-238","Timezone":"Asia/Shanghai","CreatedAt":"2025-06-22T22:36:59.573479+04:00"},
{"ID":252,"Name":"user-252","Timezone":"Asia/Shanghai","CreatedAt":"2025-06-22T22:36:59.673498+04:00"},
{"ID":652,"Name":"user-652","Timezone":"Asia/Shanghai","CreatedAt":"2025-06-22T22:36:59.773441+04:00"},
{"ID":431,"Name":"user-431","Timezone":"Asia/Shanghai","CreatedAt":"2025-06-22T22:36:59.87349+04:00"},
{"ID":775,"Name":"user-775","Timezone":"Asia/Shanghai","CreatedAt":"2025-06-22T22:36:59.973579+04:00"},
{"ID":457,"Name":"user-457","Timezone":"Asia/Shanghai","CreatedAt":"2025-06-22T22:37:00.072699+04:00"},
{"ID":383,"Name":"user-383","Timezone":"Asia/Shanghai","CreatedAt":"2025-06-22T22:37:00.173447+04:00"},
{"ID":119,"Name":"user-119","Timezone":"Asia/Shanghai","CreatedAt":"2025-06-22T22:37:00.273489+04:00"},
{"ID":169,"Name":"user-169","Timezone":"Asia/Shanghai","CreatedAt":"2025-06-22T22:37:00.372649+04:00"},
{"ID":885,"Name":"user-885","Timezone":"Asia/Shanghai","CreatedAt":"2025-06-22T22:37:00.473431+04:00"},
{"ID":67,"Name":"user-67","Timezone":"Asia/Shanghai","CreatedAt":"2025-06-22T22:37:00.573443+04:00"},
{"ID":421,"Name":"user-421","Timezone":"Asia/Shanghai","CreatedAt":"2025-06-22T22:37:00.673455+04:00"},
{"ID":501,"Name":"user-501","Timezone":"Asia/Shanghai","CreatedAt":"2025-06-22T22:37:00.772488+04:00"},
{"ID":169,"Name":"user-169","Timezone":"Asia/Shanghai","CreatedAt":"2025-06-22T22:37:00.873101+04:00"},
{"ID":258,"Name":"user-258","Timezone":"Asia/Shanghai","CreatedAt":"2025-06-22T22:37:00.973352+04:00"},
{"ID":593,"Name":"user-593","Timezone":"Asia/Shanghai","CreatedAt":"2025-06-22T22:37:01.073389+04:00"},
{"ID":302,"Name":"user-302","Timezone":"Asia/Shanghai","CreatedAt":"2025-06-22T22:37:01.173406+04:00"},
{"ID":913,"Name":"user-913","Timezone":"Asia/Shanghai","CreatedAt":"2025-06-22T22:37:01.273406+04:00"},
{"ID":162,"Name":"user-162","Timezone":"Asia/Shanghai","CreatedAt":"2025-06-22T22:37:01.37334+04:00"},
{"ID":370,"Name":"user-370","Timezone":"Asia/Shanghai","CreatedAt":"2025-06-22T22:37:01.473395+04:00"},
{"ID":798,"Name":"user-798","Timezone":"Asia/Shanghai","CreatedAt":"2025-06-22T22:37:01.573386+04:00"},
{"ID":90,"Name":"user-90","Timezone":"Asia/Shanghai","CreatedAt":"2025-06-22T22:37:01.673387+04:00"},
{"ID":183,"Name":"user-183","Timezone":"Asia/Shanghai","CreatedAt":"2025-06-22T22:37:01.773359+04:00"},
{"ID":977,"Name":"user-977","Timezone":"Asia/Shanghai","CreatedAt":"2025-06-22T22:37:01.873406+04:00"},
{"ID":309,"Name":"user-309","Timezone":"Asia/Shanghai","CreatedAt":"2025-06-22T22:37:01.973346+04:00"},
{"ID":642,"Name":"user-642","Timezone":"Asia/Shanghai","CreatedAt":"2025-06-22T22:37:02.073287+04:00"},
{"ID":917,"Name":"user-917","Timezone":"Asia/Shanghai","CreatedAt":"2025-06-22T22:37:02.173346+04:00"},
{"ID":146,"Name":"user-146","Timezone":"Asia/Shanghai","CreatedAt":"2025-06-22T22:37:02.273381+04:00"},
{"ID":619,"Name":"user-619","Timezone":"Asia/Shanghai","CreatedAt":"2025-06-22T22:37:02.373391+04:00"},
{"ID":128,"Name":"user-128","Timezone":"Asia/Shanghai","CreatedAt":"2025-06-22T22:37:02.472917+04:00"},
{"ID":931,"Name":"user-931","Timezone":"Asia/Shanghai","CreatedAt":"2025-06-22T22:37:02.573384+04:00"},
{"ID":599,"Name":"user-599","Timezone":"Asia/Shanghai","CreatedAt":"2025-06-22T22:37:02.673374+04:00"},
{"ID":40,"Name":"user-40","Timezone":"Asia/Shanghai","CreatedAt":"2025-06-22T22:37:02.773322+04:00"},
{"ID":812,"Name":"user-812","Timezone":"Asia/Shanghai","CreatedAt":"2025-06-22T22:37:02.873329+04:00"},
{"ID":509,"Name":"user-509","Timezone":"Asia/Shanghai","CreatedAt":"2025-06-22T22:37:02.973366+04:00"},
{"ID":536,"Name":"user-536","Timezone":"Asia/Shanghai","CreatedAt":"2025-06-22T22:37:03.073358+04:00"},
{"ID":286,"Name":"user-286","Timezone":"Asia/Shanghai","CreatedAt":"2025-06-22T22:37:03.173351+04:00"},
{"ID":698,"Name":"user-698","Timezone":"Asia/Shanghai","CreatedAt":"2025-06-22T22:37:03.273335+04:00"},
{"ID":543,"Name":"user-543","Timezone":"Asia/Shanghai","CreatedAt":"2025-06-22T22:37:03.373299+04:00"},
{"ID":962,"Name":"user-962","Timezone":"Asia/Shanghai","CreatedAt":"2025-06-22T22:37:03.473375+04:00"},
{"ID":94,"Name":"user-94","Timezone":"Asia/Shanghai","CreatedAt":"2025-06-22T22:37:03.573275+04:00"},
{"ID":904,"Name":"user-904","Timezone":"Asia/Shanghai","CreatedAt":"2025-06-22T22:37:03.673291+04:00"},
{"ID":863,"Name":"user-863","Timezone":"Asia/Shanghai","CreatedAt":"2025-06-22T22:37:03.773319+04:00"},
{"ID":783,"Name":"user-783","Timezone":"Asia/Shanghai","CreatedAt":"2025-06-22T22:37:03.87332+04:00"},
{"ID":124,"Name":"user-124","Timezone":"Asia/Shanghai","CreatedAt":"2025-06-22T22:37:03.973275+04:00"},
{"ID":451,"Name":"user-451","Timezone":"Asia/Shanghai","CreatedAt":"2025-06-22T22:37:04.073274+04:00"},
{"ID":25,"Name":"user-25","Timezone":"Asia/Shanghai","CreatedAt":"2025-06-22T22:37:04.173305+04:00"},
{"ID":964,"Name":"user-964","Timezone":"Asia/Shanghai","CreatedAt":"2025-06-22T22:37:04.273323+04:00"},
{"ID":64,"Name":"user-64","Timezone":"Asia/Shanghai","CreatedAt":"2025-06-22T22:37:04.373273+04:00"},
{"ID":188,"Name":"user-188","Timezone":"Asia/Shanghai","CreatedAt":"2025-06-22T22:37:04.473258+04:00"},
{"ID":82359,"Name":"John","Timezone":"US","CreatedAt":"2025-06-27T16:21:35.678299+04:00"},
{"ID":0,"Name":"John S","Timezone":"US","CreatedAt":"0001-01-01T00:00:00Z"},
{"ID":0,"Name":"John S","Timezone":"US","CreatedAt":"0001-01-01T00:00:00Z"},
{"ID":0,"Name":"John B","Timezone":"US","CreatedAt":"0001-01-01T00:00:00Z"},
{"ID":1,"Name":"John B","Timezone":"US","CreatedAt":"2025-06-27T23:02:30.441146+04:00"},
{"ID":1,"Name":"John B","Timezone":"US","CreatedAt":"2025-06-27T23:02:37.728011+04:00"},
{"ID":1,"Name":"John B","Timezone":"US","CreatedAt":"2025-06-27T23:08:00.502501+04:00"},
{"ID":2,"Name":"John B","Timezone":"US","CreatedAt":"2025-06-27T23:08:06.219255+04:00"},
{"ID":3,"Name":"John B","Timezone":"US","CreatedAt":"2025-06-27T23:08:11.199567+04:00"},
{"ID":1,"Name":"John B","Timezone":"US","CreatedAt":"2025-06-27T23:18:36.32502+04:00"},
{"ID":1,"Name":"John B","Timezone":"US","CreatedAt":"2025-06-27T23:42:50.421132+04:00"},
{"ID":2,"Name":"John B","Timezone":"US","CreatedAt":"2025-06-27T23:42:57.498714+04:00"},
{"ID":3,"Name":"John B","Timezone":"US","CreatedAt":"2025-06-27T23:43:02.220455+04:00"},
